daq_loader/__init__.py
daq_loader/demodulation.py
daq_loader/load.py
daq_loader/load_bigrig.py
probe_loader/__init__.py
probe_loader/load_probe.py
daq_loader-0.1.2.dist-info/LICENSE
daq_loader-0.1.2.dist-info/METADATA
daq_loader-0.1.2.dist-info/WHEEL
daq_loader-0.1.2.dist-info/top_level.txt
daq_loader-0.1.2.dist-info/RECORD
